fits2hdf/__init__.py
fits2hdf/check_file_type.py
fits2hdf/file_conversion.py
fits2hdf/idi.py
fits2hdf/printlog.py
fits2hdf/pyhdfits.py
fits2hdf/unit_conversion.py
fits2hdf/io/__init__.py
fits2hdf/io/fitsio.py
fits2hdf/io/hdfcompress.py
fits2hdf/io/hdfio.py
fits2hdf/io/msio.py
fits2hdf-1.1.1.dist-info/METADATA
fits2hdf-1.1.1.dist-info/RECORD
fits2hdf-1.1.1.dist-info/WHEEL
fits2hdf-1.1.1.dist-info/entry_points.txt
fits2hdf-1.1.1.dist-info/top_level.txt
