Metadata-Version: 2.1
Name: fits2hdf
Version: 1.1.1
Summary: FITS to HDF5 conversion utility
Home-page: http://github.com/telegraphic/fits2hdf
Author: Danny Price
Author-email: dancpr@berkeley.edu
License: MIT
Download-URL: https://github.com/telegraphic/hickle/archive/1.1.1.tar.gz
Platform: UNKNOWN
Requires-Python: >=3.5
Requires-Dist: h5py
Requires-Dist: astropy
Requires-Dist: colorama
